heads_up-1.0.7.dist-info/METADATA
heads_up-1.0.7.dist-info/RECORD
heads_up-1.0.7.dist-info/WHEEL
heads_up-1.0.7.dist-info/entry_points.txt
heads_up-1.0.7.dist-info/top_level.txt
headsup/__init__.py
headsup/__main__.py
headsup/config.txt
headsup/local.py
headsup/remote.py
headsup/sounds/Bsmith44.wav
