Metadata-Version: 2.1
Name: heads-up
Version: 1.0.7
Summary: Receive alerts locally and remotely at certain stages of your code execution.
Home-page: https://github.com/heads-up-org/heads-up
Author: Deniz Iren
Author-email: deniziren@gmail.com
License: MIT
Platform: UNKNOWN
Classifier: License :: OSI Approved :: MIT License
Classifier: Programming Language :: Python :: 3
Classifier: Programming Language :: Python :: 3.7
Requires-Dist: requests
Requires-Dist: pynput
Requires-Dist: playsound
Requires-Dist: qrcode[pil]
Requires-Dist: numpy
Requires-Dist: matplotlib
